cwafctl/__init__.py
cwafctl/cwafctl.py
cwafctl-0.8.0.dist-info/entry_points.txt
cwafctl-0.8.0.dist-info/WHEEL
cwafctl-0.8.0.dist-info/METADATA
cwafctl-0.8.0.dist-info/RECORD
